[
  {
    "name": "J. Curtis Creighton",
    "college": "College of Engineering and Sciences",
    "department": "Biological Sciences",
    "ongoing_research": [
      "Cell and Molecular Biology",
      "Ecology and Evolution"
    ]
  },
  {
    "name": "Ernest Talarico",
    "college": "College of Engineering and Sciences",
    "department": "Biological Sciences",
    "ongoing_research": [
      "Anatomy",
      "Physiology"
    ]
  },
  {
    "name": "Mitchell S. Alix",
    "college": "College of Engineering and Sciences",
    "department": "Biological Sciences",
    "ongoing_research": [
      "Ecology",
      "Evolution"
    ]
  },
  {
    "name": "Michael I. Zimmer",
    "college": "College of Engineering and Sciences",
    "department": "Biological Sciences",
    "ongoing_research": [
      "Human Health",
      "Clinical Research"
    ]
  },
  {
    "name": "Barbara Mania-Farnell",
    "college": "College of Engineering and Sciences",
    "department": "Biological Sciences",
    "ongoing_research": [
      "Transcription Factors",
      "Neural Tube Development"
    ]
  },
  {
    "name": "John Durocher",
    "college": "College of Engineering and Sciences",
    "department": "Biological Sciences",
    "ongoing_research": [
      "Integrative Human Health",
      "Physiology"
    ]
  },
  {
    "name": "Neeti Parashar",
    "college": "College of Engineering and Sciences",
    "department": "Chemistry and Physics",
    "ongoing_research": [
      "Higgs Boson",
      "Fundamental Physics"
    ]
  },
  {
    "name": "James W. Dolen",
    "college": "College of Engineering and Sciences",
    "department": "Chemistry and Physics",
    "ongoing_research": [
      "Particle Physics",
      "LHC Experiments"
    ]
  },
  {
    "name": "Reynaldo Barreto",
    "college": "College of Engineering and Sciences",
    "department": "Chemistry and Physics",
    "ongoing_research": [
      "Photocatalysis",
      "Environmental Remediation"
    ]
  },
  {
    "name": "Charles Steele",
    "college": "College of Engineering and Sciences",
    "department": "Chemistry and Physics",
    "ongoing_research": [
      "Forensic Science",
      "Fingerprint Development"
    ]
  },
  {
    "name": "Shuhui Grace Yang",
    "college": "College of Engineering and Sciences",
    "department": "Computer Science",
    "ongoing_research": [
      "Wireless Networking",
      "Mobile Computing"
    ]
  },
  {
    "name": "Wei David Dai",
    "college": "College of Engineering and Sciences",
    "department": "Computer Science",
    "ongoing_research": [
      "Machine Learning",
      "Data Mining"
    ]
  },
  {
    "name": "Shafkat Islam",
    "college": "College of Engineering and Sciences",
    "department": "Computer Science",
    "ongoing_research": [
      "Cybersecurity",
      "Network Security"
    ]
  },
  {
    "name": "Magesh Chandramouli",
    "college": "College of Technology",
    "department": "Computer Graphics Technology",
    "ongoing_research": [
      "Computer Graphics",
      "Virtual Reality",
      "Fulbright Research"
    ]
  },
  {
    "name": "Ali Alavizadeh",
    "college": "College of Technology",
    "department": "Industrial Engineering Technology",
    "ongoing_research": [
      "System Simulation",
      "Process Improvement"
    ]
  },
  {
    "name": "Ricardo Calix",
    "college": "College of Technology",
    "department": "Computer Information Technology",
    "ongoing_research": [
      "Machine Learning",
      "Cybersecurity"
    ]
  },
  {
    "name": "Michael R. Lynn",
    "college": "College of Humanities, Education and Social Sciences",
    "department": "History",
    "ongoing_research": [
      "Enlightenment Europe",
      "History of Science"
    ]
  },
  {
    "name": "Yu Ouyang",
    "college": "College of Humanities, Education and Social Sciences",
    "department": "Political Science",
    "ongoing_research": [
      "American Presidency",
      "Public Opinion"
    ]
  },
  {
    "name": "Amlan Mitra",
    "college": "College of Humanities, Education and Social Sciences",
    "department": "Economics",
    "ongoing_research": [
      "Economic Development",
      "Quantitative Methods"
    ]
  },
  {
    "name": "Meg Bergin Rincker",
    "college": "College of Humanities, Education and Social Sciences",
    "department": "Political Science",
    "ongoing_research": [
      "Comparative Politics",
      "Gender and Politics"
    ]
  }
]